setup.py
sphinxfeed.py
sphinxfeed.egg-info/PKG-INFO
sphinxfeed.egg-info/SOURCES.txt
sphinxfeed.egg-info/dependency_links.txt
sphinxfeed.egg-info/requires.txt
sphinxfeed.egg-info/top_level.txt