Metadata-Version: 1.0
Name: sphinxfeed
Version: 0.2
Summary: Sphinx extension for generating RSS feeds
Home-page: https://github.com/junkafarian/sphinxfeed
Author: junkafarian
Author-email: junkafarian@gmail.com
License: BSD
Platform: any
Classifier: Development Status :: 4 - Beta
Classifier: Environment :: Console
Classifier: Environment :: Web Environment
Classifier: Intended Audience :: Developers
Classifier: License :: OSI Approved :: BSD License
Classifier: Operating System :: OS Independent
Classifier: Programming Language :: Python
Classifier: Topic :: Documentation
Classifier: Topic :: Utilities
